aoj/__init__.py
aoj/__main__.py
aoj_api-0.2.4.dist-info/entry_points.txt
aoj_api-0.2.4.dist-info/LICENSE
aoj_api-0.2.4.dist-info/WHEEL
aoj_api-0.2.4.dist-info/METADATA
aoj_api-0.2.4.dist-info/RECORD
